llama_index/readers/txtai/__init__.py
llama_index/readers/txtai/base.py
llama_index_readers_txtai-0.4.1.dist-info/METADATA
llama_index_readers_txtai-0.4.1.dist-info/WHEEL
llama_index_readers_txtai-0.4.1.dist-info/licenses/LICENSE
llama_index_readers_txtai-0.4.1.dist-info/RECORD
